jodium/__init__.py
jodium/auto_electron.py
jodium/install_driver.py
jodium/jodium.py
jodium/mirror.py
jodium/selenium.py
jodium/webdriver_manager.py
jodium-0.1.0.dist-info/LICENSE
jodium-0.1.0.dist-info/METADATA
jodium-0.1.0.dist-info/WHEEL
jodium-0.1.0.dist-info/RECORD
